faster_sam/__init__.py
faster_sam/adapter.py
faster_sam/cloudformation.py
faster_sam/helpers.py
faster_sam/lambda_event.py
faster_sam/openapi.py
faster_sam/protocols.py
faster_sam/routing.py
faster_sam/schemas.py
faster_sam/utils.py
faster_sam/web_identity_providers.py
faster_sam/cache/__init__.py
faster_sam/cache/cache_interface.py
faster_sam/cache/redis_cache.py
faster_sam/cmd/__init__.py
faster_sam/cmd/faster.py
faster_sam/dependencies/__init__.py
faster_sam/dependencies/events.py
faster_sam/middlewares/__init__.py
faster_sam/middlewares/bucket_path_rewriter.py
faster_sam/middlewares/lambda_authorizer.py
faster_sam/middlewares/queue_path_rewriter.py
faster_sam/middlewares/remove_path.py
faster_sam-0.15.0.dist-info/LICENSE
faster_sam-0.15.0.dist-info/METADATA
faster_sam-0.15.0.dist-info/WHEEL
faster_sam-0.15.0.dist-info/entry_points.txt
faster_sam-0.15.0.dist-info/top_level.txt
faster_sam-0.15.0.dist-info/RECORD
