Metadata-Version: 2.1
Name: faster-sam
Version: 0.15.0
Summary: An adapter to enable running APIs built with AWS SAM applications using FastAPI.
Author-email: Dotz Developers <devs-dotz@dotz.com>
License: MIT
Keywords: utilities,fastapi,sam
Classifier: Programming Language :: Python :: 3
Requires-Python: >=3.8
License-File: LICENSE
Requires-Dist: fastapi
Requires-Dist: PyYAML
Provides-Extra: auth
Requires-Dist: boto3 ; extra == 'auth'
Requires-Dist: requests ; extra == 'auth'
Provides-Extra: migrate
Requires-Dist: yoyo-migrations ; extra == 'migrate'
Requires-Dist: setuptools ; extra == 'migrate'
Provides-Extra: redis
Requires-Dist: redis ; extra == 'redis'
